ndip_checker/__init__.py
ndip_checker/main.py
ndip_checker/parser.py
ndip_checker/treatment.py
ndip_checker/items/__init__.py
ndip_checker/items/base.py
ndip_checker/items/bingchengjilu.py
ndip_checker/items/factory.py
ndip_checker/items/peiyang.py
ndip_checker/items/tupian.py
ndip_checker-1.0.0.data/scripts/main.py
src/__init__.py
src/main.py
src/parser.py
src/treatment.py
src/items/__init__.py
src/items/base.py
src/items/bingchengjilu.py
src/items/factory.py
src/items/peiyang.py
src/items/tupian.py
ndip_checker-1.0.0.dist-info/LICENSE
ndip_checker-1.0.0.dist-info/METADATA
ndip_checker-1.0.0.dist-info/WHEEL
ndip_checker-1.0.0.dist-info/entry_points.txt
ndip_checker-1.0.0.dist-info/top_level.txt
ndip_checker-1.0.0.dist-info/RECORD
