Metadata-Version: 2.1
Name: ndip-checker
Version: 1.0.0
Summary: check and fix errors in NDIP
Home-page: https://gitee.com/yarving/NdipChecker
Author: Yarving Liu
Author-email: yarving@gmail.com
License: UNKNOWN
Platform: UNKNOWN
Classifier: Programming Language :: Python :: 2.7
Classifier: License :: OSI Approved :: MIT License
Classifier: Operating System :: OS Independent
Requires-Dist: MySQL-python
